drf_http_serialization/__init__.py
drf_http_serialization/core.py
drf_http_serialization/models.py
drf_http_serialization/serializers.py
drf_http_serialization/settings.py
drf_http_serialization-1.0.1.dist-info/LICENSE
drf_http_serialization-1.0.1.dist-info/METADATA
drf_http_serialization-1.0.1.dist-info/WHEEL
drf_http_serialization-1.0.1.dist-info/top_level.txt
drf_http_serialization-1.0.1.dist-info/RECORD
